ebsdtorch/__init__.py
ebsdtorch/ebsd_dictionary_indexing/__init__.py
ebsdtorch/ebsd_dictionary_indexing/blur_master_pattern_direct.py
ebsdtorch/ebsd_dictionary_indexing/ebsd_di_one_pc_one_phase.py
ebsdtorch/ebsd_dictionary_indexing/ebsd_di_one_pc_one_phase_pca.py
ebsdtorch/ebsd_dictionary_indexing/ebsd_di_spherical_covmat.py
ebsdtorch/ebsd_dictionary_indexing/utils_covariance_matrix.py
ebsdtorch/ebsd_dictionary_indexing/utils_nearest_neighbors.py
ebsdtorch/ebsd_dictionary_indexing/utils_progress_bar.py
ebsdtorch/ebsd_high_resolution/__init__.py
ebsdtorch/ebsd_high_resolution/hrebsd_project.py
ebsdtorch/patterns/__init__.py
ebsdtorch/patterns/lie_algebra_se3.py
ebsdtorch/patterns/lie_algebra_sim3_with_stretch.py
ebsdtorch/patterns/pattern_projection.py
ebsdtorch/patterns/square_hemisphere_bijection.py
ebsdtorch/s2_and_so3/__init__.py
ebsdtorch/s2_and_so3/laue.py
ebsdtorch/s2_and_so3/orientations.py
ebsdtorch/s2_and_so3/sampling.py
ebsdtorch/simulation/monte_carlo_simulation.py
ebsdtorch/spherical/extended_precision.py
ebsdtorch/spherical/spherical_harmonic_transform.py
ebsdtorch/spherical/test_ts2kit_wigner.py
ebsdtorch/spherical/wigner_d_coeff.py
ebsdtorch/spherical/wigner_d_coeff_Fukushima.py
ebsdtorch/spherical/wigner_d_coeff_spherical.py
ebsdtorch/spherical/wigner_d_coeffs_Lenthe.py
ebsdtorch/spherical/wigner_naive.py
ebsdtorch-0.1.1.dist-info/LICENSE
ebsdtorch-0.1.1.dist-info/METADATA
ebsdtorch-0.1.1.dist-info/WHEEL
ebsdtorch-0.1.1.dist-info/RECORD
