Metadata-Version: 2.1
Name: ebsdtorch
Version: 0.1.1
Summary: 
Author: Zachary Varley
Author-email: zvarley@andrew.cmu.edu
Requires-Python: >=3.10,<4.0
Classifier: Programming Language :: Python :: 3
Classifier: Programming Language :: Python :: 3.10
Classifier: Programming Language :: Python :: 3.11
Requires-Dist: torch (>=2.1.0,<3.0.0)
